partial_injector/__init__.py
partial_injector/CHANGELOG.md
partial_injector/error_handling.py
partial_injector/LICENSE
partial_injector/partial_container.py
partial_injector/poetry.lock
partial_injector-3.2.3.dist-info/METADATA
partial_injector-3.2.3.dist-info/WHEEL
partial_injector-3.2.3.dist-info/RECORD
